pwncollege/__init__.py
pwncollege/challenge.py
pwncollege/constants.py
pwncollege/errors.py
pwncollege/leaderboard.py
pwncollege/pwncli/__init__.py
pwncollege/pwncli/challenge.py
pwncollege/pwncli/get.py
pwncollege/pwncli/profile.py
pwncollege/pwncollege.py
pwncollege/user.py
pwncollege/utils.py
pypwncollege-0.1.7.dist-info/LICENSE
pypwncollege-0.1.7.dist-info/METADATA
pypwncollege-0.1.7.dist-info/WHEEL
pypwncollege-0.1.7.dist-info/entry_points.txt
pypwncollege-0.1.7.dist-info/RECORD
