Metadata-Version: 2.1
Name: PyPwnCollege
Version: 0.1.7
Summary: A wrapper for the pwn.college API. This allows automating interactions with pwn.college and also includes a command-line-interface(CLI) to list dojos/modules, submit flags, start challenges, run commands in challenge containers and more.
Home-page: https://pypwncollege.readthedocs.io/
Keywords: pwn.college,pwncollege,automation
Author: Zeeshan Ayub
Author-email: mayub9799@gmail.com
Requires-Python: >=3.8,<4.0
Classifier: Programming Language :: Python :: 3
Classifier: Programming Language :: Python :: 3.8
Classifier: Programming Language :: Python :: 3.9
Classifier: Programming Language :: Python :: 3.10
Classifier: Programming Language :: Python :: 3.11
Classifier: Programming Language :: Python :: 3.12
Requires-Dist: paramiko (>=3.0.0,<4.0.0)
Requires-Dist: requests (>=2.0.0,<3.0.0)
Project-URL: Documentation, https://pypwncollege.readthedocs.io/
Project-URL: Repository, https://github.com/zeeshan12340/pypwncollege
